{
  "source_url": "https://thuvienphapluat.vn/van-ban/Doanh-nghiep/Nghi-dinh-01-2021-ND-CP-dang-ky-doanh-nghiep-283247.aspx",
  "meta": {
    "Tiêu đề": "Nghị định 01/2021/NĐ-CP về đăng ký doanh nghiệp",
    "Số hiệu": "01/2021/NĐ-CP",
    "Loại văn bản": "Nghị định",
    "Lĩnh vực, ngành": "Doanh nghiệp",
    "Nơi ban hành": "Chính phủ",
    "Người ký": "Nguyễn Xuân Phúc",
    "Ngày ban hành": "04/01/2021",
    "Ngày hiệu lực": "Đã biết",
    "Ngày đăng": "24/01/2021",
    "Số công báo": "Từ số 113 đến số 114",
    "Tình trạng": "Đã biết",
    "Tóm tắt văn bản": "Yêu cầu đối với hồ sơ đăng ký doanh nghiệp qua mạng Ngày 04/01/2021, Chính phủ ban hành Nghị định 01/2021/NĐ-CP về đăng ký doanh nghiệp.Theo đó, hồ sơ đăng ký doanh nghiệp (ĐKDN) qua mạng thông tin điện tử được chấp thuận khi có đầy đủ các yêu cầu sau: - Có đầy đủ các giấy tờ và nội dung các giấy tờ đó được kê khai đầy đủ theo quy định như hồ sơ bằng bản giấy và được thể hiện dưới dạng văn bản điện tử; - Tên văn bản điện tử phải được đặt tương ứng với tên loại giấy tờ trong hồ sơ bằng bản giấy; phần chữ ký trong hồ sơ có thể sử dụng chữ ký số hoặc ký trực tiếp và thực hiện scan. - Các thông tin ĐKDN được kê khai trên Cổng thông tin quốc gia về ĐKDN phải đầy đủ và chính xác theo các thông tin trong hồ sơ bằng bản giấy; có bao gồm thông tin về SĐT, thư điện tử của người nộp hồ sơ (quy định mới); - Hồ sơ ĐKDN qua mạng phải được xác thực bằng chữ ký số hoặc Tài khoản đăng ký kinh doanh của người có thẩm quyền ký văn bản đề nghị ĐKDN hoặc người được ủy quyền. Nghị định 01/2021/NĐ-CP có hiệu lực thi hành từ ngày 04/01/2021. >> XEM BẢN TIẾNG ANH CỦA BÀI VIẾT NÀY TẠI ĐÂY"
  },
  "relations_sections": {
    "guidedDocument | Văn bản được hướng dẫn -": [],
    "DuocHopNhatDocument | Văn bản được hợp nhất -": [],
    "amendedDocument | Văn bản bị sửa đổi bổ sung -": [],
    "correctedDocument | Văn bản bị đính chính -": [],
    "replacedDocument | Văn bản bị thay thế -": [],
    "referentialDocument | Văn bản được dẫn chiếu -": [],
    "basisDocument | Văn bản được căn cứ -": [],
    "guideDocument | Văn bản hướng dẫn -": [],
    "HopNhatDocument | Văn bản hợp nhất -": [],
    "amendDocument | Văn bản sửa đổi bổ sung -": [],
    "correctingDocument | Văn bản đính chính -": [],
    "replaceDocument | Văn bản thay thế -": []
  },
  "content_connection": []
}